LICENSE
MANIFEST.in
README.rst
pyproject.toml
setup.cfg
setup.py
data_gateways/__init__.py
data_gateways/admin.py
data_gateways/apps.py
data_gateways/models.py
data_gateways/tests.py
data_gateways/core/__init__.py
data_gateways/core/registry.py
data_gateways/core/db_initializer/__init__.py
data_gateways/core/db_initializer/module_synchronizer.py
data_gateways/core/db_initializer/config_initializer/__init__.py
data_gateways/core/db_initializer/config_initializer/general_config_initializer.py
data_gateways/core/db_initializer/config_initializer/block_config_initializer/__init__.py
data_gateways/core/db_initializer/config_initializer/block_config_initializer/abstract_block_config_initializer.py
data_gateways/core/db_initializer/config_initializer/block_config_initializer/data_gateway_configs_initializer.py
data_gateways/core/db_initializer/config_initializer/block_config_initializer/sender_configs_initializer.py
data_gateways/core/db_initializer/config_initializer/block_config_initializer/strategy_configs_initializer.py
data_gateways/interfaces/__init__.py
data_gateways/interfaces/module_informative.py
data_gateways/interfaces/sendable.py
data_gateways/management/__init__.py
data_gateways/management/commands/__init__.py
data_gateways/management/commands/message_sender_init_db.py
data_gateways/message_builder/__init__.py
data_gateways/message_builder/abstract_message_builder.py
data_gateways/message_builder/default_message_builder.py
data_gateways/message_dao/__init__.py
data_gateways/message_dao/base_message_dao.py
data_gateways/message_dao/default_message_dao.py
data_gateways/migrations/0001_initial.py
data_gateways/migrations/__init__.py
data_gateways/reporters/__init__.py
data_gateways/reporters/sending_report.py
data_gateways/sending/__init__.py
data_gateways/sending/base_sendable_object.py
data_gateways/sending/send_exception_catcher.py
data_gateways/sending/senders/__init__.py
data_gateways/sending/senders/abstract_sender.py
django_data_gateways.egg-info/PKG-INFO
django_data_gateways.egg-info/SOURCES.txt
django_data_gateways.egg-info/dependency_links.txt
django_data_gateways.egg-info/requires.txt
django_data_gateways.egg-info/top_level.txt
