Metadata-Version: 2.1
Name: django-data-gateways
Version: 0.1
Summary: Django application for creating configurable data gateways in a project.
Home-page: https://www.example.com/
Author: Bobrov Alexey Pavlovich
Author-email: bobrov.bobrov-alex@yandex.ru
License: MIT
Platform: UNKNOWN
Classifier: Environment :: Web Environment
Classifier: Framework :: Django
Classifier: Framework :: Django :: 4.1
Classifier: Intended Audience :: Developers
Classifier: License :: OSI Approved :: MIT License
Classifier: Operating System :: OS Independent
Classifier: Programming Language :: Python
Classifier: Programming Language :: Python :: 3.10
Classifier: Topic :: Internet :: WWW/HTTP
Classifier: Topic :: Internet :: WWW/HTTP :: Dynamic Content
Requires-Python: >=3.10
License-File: LICENSE
